{
  "id": 620928172,
  "txt": [
    {
      "id": 228870261,
      "en": "Self Starter",
      "es": ""
    },
    {
      "id": 54354734,
      "en": "You draw strength from within and find motivation that will carry you further than before.",
      "es": ""
    },
    {
      "id": 22075073,
      "en": "Use Self-motivation",
      "es": ""
    },
    {
      "id": 118018273,
      "en": "'I find that necessity is an excellent motivator.' -- Gronir, dwarf stone-keeper",
      "es": ""
    }
  ]
}