{
  "id": 620759245,
  "txt": [
    {
      "id": 228870261,
      "en": "Of Leaf and Twig[n]",
      "es": ""
    },
    {
      "id": 54354734,
      "en": "A legendary book of lore, describing the many flora of Middle-earth in such detail that it must have taken many lifetimes deep among the forests to collect it all.\\n\\nThis book automatically starts a class deed and will be consumed upon purchase.",
      "es": ""
    },
    {
      "id": 98907573,
      "en": "Of Leaf and Twig[n]",
      "es": ""
    }
  ]
}