{
  "id": 621069021,
  "txt": [
    {
      "id": "0xd082ba4",
      "en": "You have fought the forces of evil and triumphed repeatedly in the lesser dark.",
      "es": "",
      "es (fem)": ""
    },
    {
      "id": "0x3178d11",
      "en": "You have fought the forces of evil and triumphed repeatedly in the lesser dark.",
      "es": "",
      "es (fem)": ""
    },
    {
      "id": "0xda44875",
      "en": "Delvings: The Road Goes Ever Onward",
      "es": "",
      "es (fem)": ""
    },
    {
      "id": "0xd6a5023",
      "en": "Complete Tier 1 Delving Missions ([placeholder]/10)",
      "es": "",
      "es (fem)": ""
    },
    {
      "id": "0xceb0112",
      "en": "Complete 10 Delving Missions on Tier 1",
      "es": "",
      "es (fem)": ""
    }
  ]
}