{
  "id": 620775270,
  "txt": [
    {
      "id": "0xda44875",
      "en": "Enmity of the Dead",
      "es": "",
      "es (fem)": ""
    },
    {
      "id": "0x33d632e",
      "en": "Since the beginning of time, fell spirits, not the least of which were the Balrogs of Morgoth, roamed the shadow-realm in service to the Enemy. Through foul sorceries, these spirits may stir the decaying bones of fallen Men, becoming terrible wights. To the race of Men, whose spirits pass beyond the world when they die, these monsters are true abominations.",
      "es": "",
      "es (fem)": ""
    },
    {
      "id": "0x150d6c1",
      "en": "Defeat wights",
      "es": "",
      "es (fem)": ""
    },
    {
      "id": "0x708d0e1",
      "en": "You  have faced many of the Dead that Walk and have broken the spells that bind the fell spirits to the rotting bones...but until the sorcerers who summoned them in the first place are destroyed, there is truly no defeating them.",
      "es": "",
      "es (fem)": ""
    }
  ]
}