{
  "id": 620779837,
  "txt": [
    {
      "id": 187542322,
      "en": "'I'll kill the [placeholder].'",
      "es": ""
    },
    {
      "id": 201542353,
      "en": "'I killed the [placeholder]!'",
      "es": ""
    },
    {
      "id": 263652289,
      "en": "'Die!'",
      "es": ""
    },
    {
      "id": 263652290,
      "en": "'Oh, but you look tasty.'",
      "es": ""
    },
    {
      "id": 187542323,
      "en": "'Time to die, [placeholder]!'",
      "es": ""
    },
    {
      "id": 201542354,
      "en": "'I killed your friend.'",
      "es": ""
    },
    {
      "id": 263652291,
      "en": "'I'll have your heart.'",
      "es": ""
    },
    {
      "id": 187542324,
      "en": "'I sees a [placeholder]!'",
      "es": ""
    },
    {
      "id": 201542355,
      "en": "'I gots me another!'",
      "es": ""
    },
    {
      "id": 99934385,
      "en": "'No! No! I've got to get help!'",
      "es": ""
    },
    {
      "id": 28737057,
      "en": "'I'll kill you myself!'",
      "es": ""
    },
    {
      "id": 99934386,
      "en": "'Ah! I must warn the others!'",
      "es": ""
    },
    {
      "id": 207977553,
      "en": "'Run for your lives!'",
      "es": ""
    },
    {
      "id": 207977554,
      "en": "'Run! They're too strong!'",
      "es": ""
    },
    {
      "id": 207977555,
      "en": "'Leave me be!'",
      "es": ""
    },
    {
      "id": 231505313,
      "en": "'Now you're in trouble!'",
      "es": ""
    },
    {
      "id": 231505314,
      "en": "'Oh, this'll be such fun.'",
      "es": ""
    },
    {
      "id": 85745745,
      "en": "'You'll pay for that!'",
      "es": ""
    },
    {
      "id": 85745746,
      "en": "'Hold 'em back!'",
      "es": ""
    },
    {
      "id": 85745747,
      "en": "'Stop gawking and start fighting!'",
      "es": ""
    },
    {
      "id": 187542321,
      "en": "'I'll gut you, [placeholder]!'",
      "es": ""
    }
  ]
}