{
  "id": 620808690,
  "txt": [
    {
      "id": 187542322,
      "en": "'Death to the Trév Gállorg!'",
      "es": ""
    },
    {
      "id": 201542353,
      "en": "'Ha! Is this the best the Trév Gállorg can offer?'",
      "es": ""
    },
    {
      "id": 263652289,
      "en": "'Aughaire shall burn!'",
      "es": ""
    },
    {
      "id": 263652290,
      "en": "'I shall relish your defeat!'",
      "es": ""
    },
    {
      "id": 187542323,
      "en": "'Aughaire shall fall!'",
      "es": ""
    },
    {
      "id": 201542354,
      "en": "'So shall all enemies of Angmar pass!'",
      "es": ""
    },
    {
      "id": 263652291,
      "en": "'You shall suffer in the prisons of Carn Dûm!'",
      "es": ""
    },
    {
      "id": 187542324,
      "en": "'I have no need for the Trév Gállorg or the Trév Duvárdain!'",
      "es": ""
    },
    {
      "id": 201542355,
      "en": "'None can resist Angmar's power!'",
      "es": ""
    },
    {
      "id": 263652292,
      "en": "'You shall not win this day!'",
      "es": ""
    },
    {
      "id": 187542325,
      "en": "'The Trév Gállorg shall pay for their insult!'",
      "es": ""
    },
    {
      "id": 201542356,
      "en": "'I shall do the same to Crannog and all the Trév Gállorg!'",
      "es": ""
    },
    {
      "id": 207947537,
      "en": "'You cannot distract me from my true goal!'",
      "es": ""
    },
    {
      "id": 85745745,
      "en": "'Pathetic fools! Do not falter!'",
      "es": ""
    },
    {
      "id": 85745746,
      "en": "'No!'",
      "es": ""
    },
    {
      "id": 85745747,
      "en": "'Press on! Aughaire must fall!'",
      "es": ""
    },
    {
      "id": 187542321,
      "en": "'I shall have my revenge!'",
      "es": ""
    }
  ]
}