{
  "id": 621095580,
  "txt": [
    {
      "id": "0x4007fe5",
      "en": "Hadhir-en-ereg\\n(Sparrow of holly)",
      "es": "",
      "es (fem)": ""
    },
    {
      "id": "0xda44875",
      "en": "Holly-sparrow[e]",
      "es": "",
      "es (fem)": ""
    },
    {
      "id": "0x33d632e",
      "en": "Class: Tree\\nSubclass: Perching\\nType: Sparrow\\nFound in: Eregion\\nHabitats: Fields, woods, thickets, pools",
      "es": "",
      "es (fem)": ""
    },
    {
      "id": "0x5e535b5",
      "en": "Holly-sparrow[e]",
      "es": "",
      "es (fem)": ""
    }
  ]
}