{
  "id": 620895705,
  "txt": [
    {
      "id": 228870261,
      "en": "Easterling-slayer (Advanced)",
      "es": ""
    },
    {
      "id": 54354734,
      "en": "Defeat many Easterlings in the Great River.",
      "es": ""
    },
    {
      "id": 22075073,
      "en": "Defeat Easterlings in the Great River",
      "es": ""
    },
    {
      "id": 118018273,
      "en": "The Easterlings have learned to fear your name...perhaps tales of your might will flow to other enemies throughout the Great River.",
      "es": ""
    }
  ]
}