{
  "id": 621093029,
  "txt": [
    {
      "id": "0x74d6f61",
      "en": "'Rothog, I DEMAND-'",
      "es": "",
      "es (fem)": ""
    },
    {
      "id": "0x6a502a5",
      "en": "Speak to Rothog",
      "es": "",
      "es (fem)": ""
    },
    {
      "id": "0x74d6f62",
      "en": "'Well, I will spill blood on this floor.'",
      "es": "",
      "es (fem)": ""
    },
    {
      "id": "0x6a502a6",
      "en": "Defeat Zarzíra and her men",
      "es": "",
      "es (fem)": ""
    },
    {
      "id": "0x9b568a4",
      "en": "'Zarzíra made a grave mistake so openly attacking you in my presence. I am overjoyed by your victory. You see, Zarzíra and her men were not worth me bloodying my blades, as they are so below me. But I commend you for your quick action.\\n\\n'Rest assured, if Shaidal is successful in the task that I laid out before him, he will go free.\\n\\n'Thank you again for helping solve what could have been a rather complicated situation!'",
      "es": "",
      "es (fem)": ""
    },
    {
      "id": "0x74d6f63",
      "en": "'I will never betray my patron.'",
      "es": "",
      "es (fem)": ""
    },
    {
      "id": "0xeb01199",
      "en": "Rothog has summoned you to his chambers to confront Zarzíra Dawn-star about her misdeeds.",
      "es": "",
      "es (fem)": ""
    },
    {
      "id": "0x7368161",
      "en": "'Zarzíra Dawn-star, I have called you to my chambers in regards to your petition.'",
      "es": "",
      "es (fem)": ""
    },
    {
      "id": "0xa8e1187",
      "en": "With Zarzíra vanquished, Rothog beckons to you",
      "es": "",
      "es (fem)": ""
    },
    {
      "id": "0x7368162",
      "en": "'I have found and dealt with the culprit. Sadly the information stolen was destroyed in the process.'",
      "es": "",
      "es (fem)": ""
    },
    {
      "id": "0x7368163",
      "en": "'YOU DEMAND NOTHING FROM ME!'",
      "es": "",
      "es (fem)": ""
    },
    {
      "id": "0x7368164",
      "en": "'If I were not as magnificent and generous as I am, I would spill your blood on this floor for your insolence.'",
      "es": "",
      "es (fem)": ""
    },
    {
      "id": "0xeb011b8",
      "en": "Speak to Rothog the Storm about Zarzíra's treachery.",
      "es": "",
      "es (fem)": ""
    },
    {
      "id": "0x6a502b1",
      "en": "Talk to Rothog the Storm",
      "es": "",
      "es (fem)": ""
    },
    {
      "id": "0x7368165",
      "en": "'I will not sully my blade. Could you dispatch this filth?'",
      "es": "",
      "es (fem)": ""
    },
    {
      "id": "0xeb011a2",
      "en": "Defeat Zarzíra and her men as they attack you in the audience chamber.",
      "es": "",
      "es (fem)": ""
    },
    {
      "id": "0x9b568b0",
      "en": "'Now you will see a matter of justice. While I am very confident about how this will go, do be wary, as this serpent seems to be willing to strike.'",
      "es": "",
      "es (fem)": ""
    },
    {
      "id": "0x7368166",
      "en": "'A shame, not even useful in death.'",
      "es": "",
      "es (fem)": ""
    },
    {
      "id": "0x3178d11",
      "en": "Rothog has summoned you to his chambers as he confronts Zarzíra Dawn-star about her misdeeds.",
      "es": "",
      "es (fem)": ""
    },
    {
      "id": "0x9b568b5",
      "en": "'I give you my thanks again [placeholder]. With Zarzíra defeated and Shaidal well on his way to freedom, things seem to have worked out. Now please go, my people have some cleaning up to do.'",
      "es": "",
      "es (fem)": ""
    },
    {
      "id": "0xda44875",
      "en": "Instance: Rothog's Fury",
      "es": "",
      "es (fem)": ""
    }
  ]
}