{
  "id": 621021893,
  "txt": [
    {
      "id": "0xda44875",
      "en": "Questionable Present, Warg Variety[e]",
      "es": "",
      "es (fem)": ""
    },
    {
      "id": "0x33d632e",
      "en": "This disgusting warg trophy does not seem like an especially satisfactory birthday present to you, but who can say how it will be received?",
      "es": "",
      "es (fem)": ""
    },
    {
      "id": "0x5e535b5",
      "en": "Questionable Presents, Warg Variety[p]",
      "es": "",
      "es (fem)": ""
    }
  ]
}