{
  "id": 620781079,
  "txt": [
    {
      "id": "0x624fe1",
      "en": "'Working a smithy in this remote place isn't exactly the Great Forge in Thorin's Hall, but it's a step forward.'",
      "es": "",
      "es (fem)": ""
    },
    {
      "id": "0x624fe2",
      "en": "'Dwarves here require tools, weapons, and armour, just as they do anywhere else.'",
      "es": "",
      "es (fem)": ""
    },
    {
      "id": "0x624fe3",
      "en": "'The sound of the hammer and anvil ringing in the hills reminds me of home.'",
      "es": "",
      "es (fem)": ""
    },
    {
      "id": "0x624fe4",
      "en": "'Don't stand too close to the forge! Wouldn't want your fancy clothes to catch fire!'",
      "es": "",
      "es (fem)": ""
    }
  ]
}